brip/__init__.py
brip/brip.py
brip-0.3.0.dist-info/LICENSE
brip-0.3.0.dist-info/METADATA
brip-0.3.0.dist-info/WHEEL
brip-0.3.0.dist-info/entry_points.txt
brip-0.3.0.dist-info/top_level.txt
brip-0.3.0.dist-info/RECORD
