Metadata-Version: 2.1
Name: brip
Version: 0.3.0
Summary: brip stands for Brython's pip. It brings the Python Package Index (PyPI) ecosystem and the pip-like workflow to Brython-powered project.
Home-page: https://github.com/rayluo/brip
Author: Ray Luo
Author-email: rayluo.mba@gmail.com
License: MIT
Project-URL: Changelog, https://github.com/rayluo/brip/releases
Keywords: pip,brython,package,install
Classifier: Development Status :: 4 - Beta
Classifier: Intended Audience :: Developers
Classifier: License :: OSI Approved :: MIT License
Classifier: Topic :: Software Development :: Build Tools
Classifier: Operating System :: OS Independent
Classifier: Programming Language :: Python
Classifier: Programming Language :: Python :: 3
Classifier: Programming Language :: Python :: 3.7
Classifier: Programming Language :: Python :: 3.8
Classifier: Programming Language :: Python :: 3.9
Classifier: Programming Language :: Python :: 3.10
Classifier: Programming Language :: Python :: 3.11
Classifier: Programming Language :: Python :: 3.12
Requires-Python: >=3.7
License-File: LICENSE
Requires-Dist: pip >=1.1
Requires-Dist: brython >=3.10.6 ; python_version >= "3.10"
Requires-Dist: brython <=3.10.5,>=3.7.5 ; python_version >= "3.7" and python_version <= "3.9"
